<?xml version="1.0" encoding="utf-8"?>
<Lib NameU="Azure Other Microsoft Prod">
    <Elem NameU="Access" Name="软件Access" PromptU="Access" Prompt="软件Access"/>
    <Elem NameU="Excel" Name="软件Excel" PromptU="Excel" Prompt="软件Excel"/>
    <Elem NameU="Exchange" Name="软件Exchange" PromptU="Exchange" Prompt="软件Exchange"/>
    <Elem NameU="Lync" Name="软件Lync" PromptU="Lync" Prompt="软件Lync"/>
    <Elem NameU="Outlook" Name="软件Outlook" PromptU="Outlook" Prompt="软件Outlook"/>
    <Elem NameU="PowerApps" Name="软件PowerApps" PromptU="PowerApps" Prompt="软件PowerApps"/>
    <Elem NameU="PowerPoint" Name="软件PowerPoint" PromptU="PowerPoint" Prompt="软件PowerPoint"/>
    <Elem NameU="Sharepoint" Name="软件Sharepoint" PromptU="Sharepoint" Prompt="软件Sharepoint"/>
    <Elem NameU="Visio" Name="软件Visio" PromptU="Visio" Prompt="软件Visio"/>
    <Elem NameU="Word" Name="软件Word" PromptU="Word" Prompt="软件Word"/>
    <Elem NameU="Cortana Blue" Name="软件Cortana Blue" PromptU="Cortana Blue" Prompt="软件Cortana Blue"/>
    <Elem NameU="BI Product" Name="软件BI Product" PromptU="BI Product" Prompt="软件BI Product"/>
</Lib>
